telemify/__init__.py
telemify/logging/__init__.py
telemify/logging/configure.py
telemify/logging/filters.py
telemify/logging/middleware.py
telemify/logging/processors.py
telemify/metrics/__init__.py
telemify/metrics/configure.py
telemify/metrics/metrics.py
telemify/metrics/middleware.py
telemify/settings.py
telemify/tracing/__init__.py
telemify/tracing/configure.py
telemify-0.5.1.dist-info/METADATA
telemify-0.5.1.dist-info/WHEEL
telemify-0.5.1.dist-info/RECORD
