Metadata-Version: 2.1
Name: telemify
Version: 0.5.1
Summary: Seamless instrumentation of tracing, logging, and metrics in FastAPI and Starlette applications, using opentelemetry structlog, and prometheus-client.
Home-page: https://github.com/portmind/telemify
Author: Portmind's ML Engineering Team
Maintainer: Sevak Harutyunyan
Maintainer-email: sevak.harutyunyan@portmind.com
Requires-Python: >=3.10,<4.0
Classifier: Programming Language :: Python :: 3
Classifier: Programming Language :: Python :: 3.10
Classifier: Programming Language :: Python :: 3.11
Classifier: Programming Language :: Python :: 3.12
Requires-Dist: msgpack (>=1.0.8,<2.0.0)
Requires-Dist: opentelemetry-distro (>=0.46b0,<0.47)
Requires-Dist: opentelemetry-exporter-otlp (>=1.25.0,<2.0.0)
Requires-Dist: opentelemetry-instrumentation-botocore (>=0.46b0,<0.47)
Requires-Dist: opentelemetry-instrumentation-celery (>=0.46b0,<0.47)
Requires-Dist: opentelemetry-instrumentation-httpx (>=0.46b0,<0.47)
Requires-Dist: opentelemetry-instrumentation-jinja2 (>=0.46b0,<0.47)
Requires-Dist: opentelemetry-instrumentation-sqlalchemy (>=0.46b0,<0.47)
Requires-Dist: opentelemetry-instrumentation-starlette (>=0.46b0,<0.47)
Requires-Dist: opentelemetry-instrumentation-threading (>=0.46b0,<0.47)
Requires-Dist: prometheus-client (>=0.20.0,<0.21.0)
Requires-Dist: starlette (>=0.37.2,<0.38.0)
Requires-Dist: structlog (>=24.2.0,<25.0.0)
Requires-Dist: urllib3 (>=2.2.2,<3.0.0)
Project-URL: Repository, https://github.com/portmind/telemify
